setup.py
cliff_rackspace/__init__.py
cliff_rackspace/command_manager.py
cliff_rackspace/formatters.py
cliff_rackspace.egg-info/PKG-INFO
cliff_rackspace.egg-info/SOURCES.txt
cliff_rackspace.egg-info/dependency_links.txt
cliff_rackspace.egg-info/namespace_packages.txt
cliff_rackspace.egg-info/top_level.txt
cliff_rackspace/commands/__init__.py
cliff_rackspace/commands/help.py