Metadata-Version: 1.1
Name: cliff-rackspace
Version: 0.1.1
Summary: Rackspace Python cliff library extensions.
Home-page: https://github.com/racker/python-cliff-rackspace
Author: Rackspace Hosting
Author-email: sr@rackspace.com
License: UNKNOWN
Platform: Any
Classifier: Development Status :: 4 - Beta
Classifier: License :: OSI Approved :: Apache Software License
Classifier: Programming Language :: Python
Classifier: Programming Language :: Python :: 2.6
Classifier: Programming Language :: Python :: 2.7
Classifier: Programming Language :: Python :: Implementation :: PyPy
Classifier: Environment :: Console
